<?xml version="1.0" encoding="utf-8"?>
<SoundBanksInfo Platform="Mac" BasePlatform="Mac" SchemaVersion="16" SoundBankVersion="150">
	<RootPaths>
		<ProjectRoot>../..</ProjectRoot>
		<SourceFilesRoot>../../.cache/Mac</SourceFilesRoot>
		<SoundBanksRoot>.</SoundBanksRoot>
		<ExternalSourcesInputFile></ExternalSourcesInputFile>
		<ExternalSourcesOutputRoot>.</ExternalSourcesOutputRoot>
	</RootPaths>
	<DialogueEvents/>
	<SoundBanks>
		<SoundBank Id="1355168291" Type="User" Language="SFX" Hash="{D326F752-7CA2-0A14-FDB1-63ECE89D0199}">
			<ShortName>Init</ShortName>
			<Path>Init.bnk</Path>
			<Plugins>
				<AudioDevices>
					<Plugin Id="2317455096" Name="No_Output" LibName="No Output" LibId="11862023"/>
					<Plugin Id="3859886410" Name="System" LibName="System" LibId="11403271"/>
				</AudioDevices>
			</Plugins>
			<Busses>
				<Bus Id="3803692087" Name="Master Audio Bus"/>
			</Busses>
		</SoundBank>
		<SoundBank Id="2641024368" Type="User" Language="SFX" Hash="{58DA8C94-2A40-7371-8125-A6ADDDAA9D1D}">
			<ShortName>SFX_SoundBank</ShortName>
			<Path>SFX_SoundBank.bnk</Path>
			<Media>
				<File Id="1065132318" Language="SFX" Streaming="false" Location="Memory">
					<ShortName>SugarRush_120bpm_4-4_Pause.wav</ShortName>
					<CachePath>SFX/SugarRush_120bpm_4-4_Pause_818F3B66.wem</CachePath>
				</File>
			</Media>
			<Events>
				<Event Id="2752533807" Name="Play_TestSound" DurationType="OneShot" DurationMin="16" DurationMax="16">
					<MediaRefs>
						<MediaRef Id="1065132318"/>
					</MediaRefs>
				</Event>
			</Events>
		</SoundBank>
	</SoundBanks>
	<FileHash>{74E4F0C3-D379-D56A-9280-78069B0F9F52}</FileHash>
</SoundBanksInfo>
